gspread_db/__init__.py
gspread_db/client.py
gspread_db/models.py
tests/__init__.py
tests/models_tests.py
gspread_db-1.2.dist-info/LICENSE
gspread_db-1.2.dist-info/METADATA
gspread_db-1.2.dist-info/WHEEL
gspread_db-1.2.dist-info/top_level.txt
gspread_db-1.2.dist-info/RECORD
