Metadata-Version: 2.1
Name: gspread-db
Version: 1.2
Summary: A database-like interface for gspread.
Home-page: https://github.com/annoys-parrot/gspread_db
Author: Alessandro Scoccia Pappagallo
Author-email: aless@ndro.xyz
License: UNKNOWN
Keywords: database google spreadsheets
Platform: UNKNOWN
Classifier: Programming Language :: Python :: 3
Classifier: License :: OSI Approved :: MIT License
Classifier: Operating System :: OS Independent
Requires-Dist: pandas
Requires-Dist: gspread
